clustanom/__init__.py
clustanom/detector.py
clustanom/utils.py
clustanom-0.1.0.dist-info/LICENSE.md
clustanom-0.1.0.dist-info/METADATA
clustanom-0.1.0.dist-info/WHEEL
clustanom-0.1.0.dist-info/top_level.txt
clustanom-0.1.0.dist-info/RECORD
