Metadata-Version: 2.2
Name: clustanom
Version: 0.1.0
Summary: ClustAnom is a Scikit-Learn compatible, clustering based anomaly detection library.
Home-page: https://github.com/dekaottoman/clustanom
Author: Teoman Berkay Ayaz
Author-email: your_email@example.com
Classifier: Programming Language :: Python :: 3
Classifier: License :: OSI Approved :: MIT License
Classifier: Operating System :: OS Independent
Requires-Python: >=3.10
License-File: LICENSE.md
Requires-Dist: scikit-learn
Requires-Dist: numpy
Dynamic: author
Dynamic: author-email
Dynamic: classifier
Dynamic: description
Dynamic: description-content-type
Dynamic: home-page
Dynamic: requires-dist
Dynamic: requires-python
Dynamic: summary
